MANIFEST.in
setup.py
django_login_as.egg-info/PKG-INFO
django_login_as.egg-info/SOURCES.txt
django_login_as.egg-info/dependency_links.txt
django_login_as.egg-info/not-zip-safe
django_login_as.egg-info/requires.txt
django_login_as.egg-info/top_level.txt
login_as/__init__.py
login_as/auth_backend.py
login_as/models.py
login_as/urls.py
login_as/views.py
login_as/templates/login_as/chooser.html