Metadata-Version: 1.0
Name: django-login-as
Version: 0.1
Summary: Django Login As any user
Home-page: http://github.com/ojii/django-login-as
Author: Jonas Obrist
Author-email: jonas.obrist@divio.ch
License: UNKNOWN
Platform: UNKNOWN
